polarscope/__init__.py
polarscope/clean.py
polarscope/datasets.py
polarscope/plots.py
polarscope/py.typed
polarscope/utils.py
polarscope/xray.py
polarscope/data/diabetes.csv
polarscope/data/titanic.csv
polarscope-1.5.0.dist-info/licenses/LICENSE
tests/__init__.py
tests/performance_benchmark.py
tests/test_comprehensive.py
polarscope-1.5.0.dist-info/METADATA
polarscope-1.5.0.dist-info/WHEEL
polarscope-1.5.0.dist-info/top_level.txt
polarscope-1.5.0.dist-info/RECORD
