Metadata-Version: 2.4
Name: polarscope
Version: 1.5.0
Summary: 🔬 Simple data inspection tools for Polars - basic X-ray analysis and utilities for DataFrames.
Author: Anders & Co.
License-Expression: MIT
Requires-Python: >=3.9
License-File: LICENSE
Requires-Dist: polars>=0.20
Requires-Dist: matplotlib>=3.7
Requires-Dist: great_tables>=0.10
Provides-Extra: plotly
Requires-Dist: plotly>=5.20; extra == "plotly"
Requires-Dist: kaleido>=0.2; extra == "plotly"
Provides-Extra: altair
Requires-Dist: altair>=5; extra == "altair"
Provides-Extra: seaborn
Requires-Dist: seaborn>=0.12; extra == "seaborn"
Provides-Extra: scipy
Requires-Dist: scipy>=1.10; extra == "scipy"
Provides-Extra: all
Requires-Dist: plotly>=5.20; extra == "all"
Requires-Dist: kaleido>=0.2; extra == "all"
Requires-Dist: altair>=5; extra == "all"
Requires-Dist: seaborn>=0.12; extra == "all"
Requires-Dist: scipy>=1.10; extra == "all"
Dynamic: license-file
